{
  "title": "DNDBeyond NPC Sheet",
  "description": "This module adds an additional NPC sheet with a clean interface reminiscent of DNDBeyond npc stat blocks.",
  "url": "https://github.com/jopeek/fvtt-dndbeyond-npc-sheet",
  "version": "11.240.1",
  "authors": [
    {
      "name": "Jan Ole Peek (ChalkOne)",
      "flags": {}
    }
  ],
  "compatibility": {
    "minimum": "11",
    "verified": "11.315",
    "maximum": "11"
  },
  "esmodules": [
    "/dndbeyond-npc-sheet.js"
  ],
  "styles": [
    "/css/dndbeyond-npc-sheet.css"
  ],
  "relationships": {
    "systems": [
      {
        "id": "dnd5e",
        "type": "system",
        "compatibility": {
          "minimum": "2.2.2",
          "verified": "2.4.0",
          "maximum": "2.9.9"
        }
      }
    ]
  },
  "manifest": "https://raw.githubusercontent.com/jopeek/fvtt-dndbeyond-npc-sheet/master/module.json",
  "download": "https://github.com/jopeek/fvtt-dndbeyond-npc-sheet/archive/master.zip",
  "id": "dndbeyond-npc-sheet"
}